Metadata-Version: 2.1
Name: DXFpy-TOOLBOX
Version: 2023.1
Summary: Hello world
Author-email: iuriffraga@gmail.com
License: Apache License
Classifier: Programming Language :: Python
Classifier: Topic :: Scientific/Engineering :: Mathematics
Classifier: Topic :: Scientific/Engineering
License-File: LICENSE
